dadapush_client/__init__.py
dadapush_client/api_client.py
dadapush_client/configuration.py
dadapush_client/exceptions.py
dadapush_client/rest.py
dadapush_client/api/__init__.py
dadapush_client/api/dadapush_message_api.py
dadapush_client/models/__init__.py
dadapush_client/models/action.py
dadapush_client/models/message_object.py
dadapush_client/models/message_push_request.py
dadapush_client/models/message_push_response.py
dadapush_client/models/page_response_of_message_object.py
dadapush_client/models/result.py
dadapush_client/models/result_of_message_object.py
dadapush_client/models/result_of_message_push_response.py
dadapush_client/models/result_of_page_response_of_message_object.py
test/__init__.py
test/test_dadapush_message_api.py
dadapush_client-1.0.2.dist-info/METADATA
dadapush_client-1.0.2.dist-info/WHEEL
dadapush_client-1.0.2.dist-info/top_level.txt
dadapush_client-1.0.2.dist-info/RECORD
